outline_cli/__init__.py
outline_cli/gmail.py
outline_cli/helper.py
outline_cli/outline.py
outline_cli/templates/__init__.py
outline_cli/templates/mail_template.txt
outline_cli-1.0.10.dist-info/LICENSE.txt
outline_cli-1.0.10.dist-info/METADATA
outline_cli-1.0.10.dist-info/WHEEL
outline_cli-1.0.10.dist-info/entry_points.txt
outline_cli-1.0.10.dist-info/top_level.txt
outline_cli-1.0.10.dist-info/zip-safe
outline_cli-1.0.10.dist-info/RECORD
