Metadata-Version: 2.1
Name: outline-cli
Version: 1.0.10
Summary: UNKNOWN
Home-page: UNKNOWN
Author: Jimmy Chen
Author-email: jimmychen260@gmail.com
License: UNKNOWN
Project-URL: Bug Tracker, https://github.com/JMCFTW/outline-cli/issues
Project-URL: Source Code, https://github.com/JMCFTW/outline-cli/
Platform: UNKNOWN
Requires-Python: >3.6
Requires-Dist: certifi ==2023.7.22
Requires-Dist: chardet ==3.0.4
Requires-Dist: idna ==2.10
Requires-Dist: requests-toolbelt ==0.9.1
Requires-Dist: urllib3 ==1.26.18
Requires-Dist: PyInquirer ==1.0.3
